gpx_reader/__init__.py
gpx_reader/_rename_MyTracks.py
gpx_reader/read.py
gpx_reader/rename.py
gpx_reader/calculate/__init__.py
gpx_reader/calculate/md5_hex.py
gpx_reader/calculate/progressbar.py
gpx_reader/filehandling/__init__.py
gpx_reader/filehandling/listing.py
gpx_reader/filehandling/operations.py
gpx_reader/validate/__init__.py
gpx_reader/validate/strings.py
gpx_reader/validate/structures.py
gpx_reader-0.3.0.dist-info/LICENSE
gpx_reader-0.3.0.dist-info/METADATA
gpx_reader-0.3.0.dist-info/WHEEL
gpx_reader-0.3.0.dist-info/top_level.txt
gpx_reader-0.3.0.dist-info/RECORD
