Metadata-Version: 2.1
Name: gpx_reader
Version: 0.3.0
Summary: A tool to read GPX files and rename the files according to the location and time of the track.
Author-email: Martin Carlos Araya <martinaraya@gmail.com>
License: MIT License
Project-URL: Homepage, https://github.com/ayaranitram/gpx_reader
Project-URL: Bug Tracker, https://github.com/ayaranitram/gpx_reader/issues
Classifier: Programming Language :: Python :: 3.7
Classifier: Programming Language :: Python :: 3.8
Classifier: Programming Language :: Python :: 3.9
Classifier: Programming Language :: Python :: 3.10
Classifier: Programming Language :: Python :: 3.11
Classifier: License :: OSI Approved :: MIT License
Classifier: Operating System :: OS Independent
Requires-Python: >=3.7
License-File: LICENSE
Requires-Dist: geopy
Requires-Dist: pandas
Requires-Dist: numpy
Requires-Dist: stringthings
